rtl/alu.v
module alu(
    input wire [2:0]    op,   //ALU Operation
    input wire [2:0]    src,  //Source register (Needed?)
    input wire [2:0]    dest, //Destination Register
    input wire [7:0]    src_data,
    input wire [7:0]    dest_data,
    input wire          size, //0 = 8-bit; 1 = 16-bit
    input wire          ext,  //CB Extension instructions
    input wire          misc, //Non-arithmetic/logic instructions
    output reg [15:0]   res,  //7:0 for 8-bit instructions
    output reg [3:0]    flags //Flag results > Flag register
    );

    //Base instructions
    localparam ADD  = 3'b000;
    localparam ADC  = 3'b001;
    localparam SUB  = 3'b010;
    localparam SBC  = 3'b011;
    localparam AND  = 3'b100;
    localparam XOR  = 3'b101;
    localparam OR   = 3'b110;
    localparam CP   = 3'b111;

    //Extensions
    localparam RLC  = 3'b000;
    localparam RRC  = 3'b001;
    localparam RL   = 3'b010;
    localparam RR   = 3'b011;
    localparam SLA  = 3'b100;
    localparam SRA  = 3'b101;
    localparam SWAP = 3'b110;
    localparam SRL  = 3'b111;

    //MISC Instructions
    localparam DAA  = 2'b00;
    localparam CPL  = 2'b01;
    localparam SCF  = 2'b10;
    localparam CCF  = 2'b11;

    //EXT+MISC Instructions
    localparam XXX  = 2'b00; //Unused
    localparam BIT  = 2'b01;
    localparam RES  = 2'b10;
    localparam SET  = 2'b11;

    //Flag Register Masks
    localparam F_ZERO  = 4'b1000;
    localparam F_SUB   = 4'b0100;
    localparam F_HALF  = 4'b0010;
    localparam F_CARRY = 4'b0001;

    always @(*) begin
        if(ext) begin //EXT instructions
            if(misc) begin //EXT+MISC instructions
                //op   = instruction[7:6]
                //src  = instruction[5:3] (encoded bit number)
                //dest = instruction[2:0] (register index)
                case(op)
                    BIT: begin
                    end

                    RES: begin
                    end

                    SET: begin
                    end
                endcase
            end else begin //EXT Arithmetic instructions
                //op   = instruction[5:3]
                //src  = instruction[2:0]
                //dest = instruction[2:0]
                case(op)
                    RLC: begin
                    end

                    RRC: begin
                    end

                    RL: begin
                    end

                    RR: begin
                    end

                    SLA: begin
                    end

                    SRA: begin
                    end

                    SWAP: begin
                    end

                    SRL: begin
                    end
                endcase
            end
        end else begin //BASE instructions
            if(misc) begin //BASE Misc instructions
                //op   = instruction[4:3]
                //src  = F register?
                //dest = F register?
                case(op)
                    DAA: begin
                    end

                    CPL: begin
                    end
                    
                    SCF: begin
                    end

                    CCF: begin
                    end
                endcase
            end else begin //BASE Non-misc instructions
                //op   = instruction[5:3]
                //src  = instruction[2:0] (register index)
                //dest = 3'b111 (A register)
                case(op)
                    ADD: begin
                        res = src_data + dest_data;
                    end

                    ADC: begin
                    end

                    SUB: begin
                    end

                    SBC: begin
                    end

                    AND: begin
                        res = src_data & dest_data;
                    end

                    XOR: begin
                        res = src_data ^ dest_data;
                    end

                    OR: begin
                        res = src_data | dest_data;
                    end

                    CP: begin
                    end
                endcase
            end
        end
    end
endmodule

sim/tb.v
`timescale 1ns / 1ns
module tb;
    reg clk;
    reg [2:0] op;
    reg [4:0] src_data;
    reg [4:0] dest_data;
    reg ext;
    reg misc;
    wire [15:0] res;
    
    alu alu1(.op(op), .src_data(src_data), .dest_data(dest_data), .ext(ext), .misc(misc), .res(res));

    integer i;
    integer j;
    integer k;
    initial begin
        j = 0;
        k = 0;
        clk = 0;
        op = 0;
        src_data = 0;
        dest_data = 0;
        ext = 0;
        misc = 0;
        while(op < 7) begin
            #5; clk = ~clk;
        end
    end

    always @(posedge clk) begin
        j = (j == 16) ? 0 : j + 1;
        src_data <= j;
        k = (j == 0) ? k + 1 : k;
        if(k == 16) begin
            k = 0;
            op <= op + 1;
        end
        dest_data <= k;
        $display("src_data=%d, dest_data=%d, res=%d", src_data, dest_data, res);
    end

    initial begin
        $dumpfile("data/dumpfile.vcd");
        $dumpvars(0, tb);
    end
endmodule

data/dumpfile.vcd
$date
	Thu Feb 20 13:15:15 2020
$end
$version
	Icarus Verilog
$end
$timescale
	1ns
$end
$scope module tb $end
$var wire 16 ! res [15:0] $end
$var reg 1 " clk $end
$var reg 5 # dest_data [4:0] $end
$var reg 1 $ ext $end
$var reg 1 % misc $end
$var reg 3 & op [2:0] $end
$var reg 5 ' src_data [4:0] $end
$var integer 32 ( j [31:0] $end
$var integer 32 ) k [31:0] $end
$scope module alu1 $end
$var wire 3 * dest [2:0] $end
$var wire 8 + dest_data [7:0] $end
$var wire 1 $ ext $end
$var wire 1 % misc $end
$var wire 3 , op [2:0] $end
$var wire 1 - size $end
$var wire 3 . src [2:0] $end
$var wire 8 / src_data [7:0] $end
$var reg 4 0 flags [3:0] $end
$var reg 16 1 res [15:0] $end
$upscope $end
$upscope $end
$enddefinitions $end
#0
$dumpvars
b0 1
bx 0
b0 /
bz .
z-
b0 ,
b0 +
bz *
b0 )
b0 (
b0 '
b0 &
0%
0$
b0 #
0"
b0 !
$end
#5
b1 !
b1 1
b1 /
b1 '
b1 (
1"
#10
0"
#15
b10 !
b10 1
b10 /
b10 '
b10 (
1"
#20
0"
#25
b11 !
b11 1
b11 /
b11 '
b11 (
1"
#30
0"
#35
b100 !
b100 1
b100 /
b100 '
b100 (
1"
#40
0"
#45
b101 !
b101 1
b101 /
b101 '
b101 (
1"
#50
0"
#55
b110 !
b110 1
b110 /
b110 '
b110 (
1"
#60
0"
#65
b111 !
b111 1
b111 /
b111 '
b111 (
1"
#70
0"
#75
b1000 !
b1000 1
b1000 /
b1000 '
b1000 (
1"
#80
0"
#85
b1001 !
b1001 1
b1001 /
b1001 '
b1001 (
1"
#90
0"
#95
b1010 !
b1010 1
b1010 /
b1010 '
b1010 (
1"
#100
0"
#105
b1011 !
b1011 1
b1011 /
b1011 '
b1011 (
1"
#110
0"
#115
b1100 !
b1100 1
b1100 /
b1100 '
b1100 (
1"
#120
0"
#125
b1101 !
b1101 1
b1101 /
b1101 '
b1101 (
1"
#130
0"
#135
b1110 !
b1110 1
b1110 /
b1110 '
b1110 (
1"
#140
0"
#145
b1111 !
b1111 1
b1111 /
b1111 '
b1111 (
1"
#150
0"
#155
b10000 !
b10000 1
b10000 /
b10000 '
b10000 (
1"
#160
0"
#165
b1 !
b1 1
b1 +
b1 #
b0 /
b0 '
b1 )
b0 (
1"
#170
0"
#175
b10 !
b10 1
b1 /
b1 '
b1 (
1"
#180
0"
#185
b11 !
b11 1
b10 /
b10 '
b10 (
1"
#190
0"
#195
b100 !
b100 1
b11 /
b11 '
b11 (
1"
#200
0"
#205
b101 !
b101 1
b100 /
b100 '
b100 (
1"
#210
0"
#215
b110 !
b110 1
b101 /
b101 '
b101 (
1"
#220
0"
#225
b111 !
b111 1
b110 /
b110 '
b110 (
1"
#230
0"
#235
b1000 !
b1000 1
b111 /
b111 '
b111 (
1"
#240
0"
#245
b1001 !
b1001 1
b1000 /
b1000 '
b1000 (
1"
#250
0"
#255
b1010 !
b1010 1
b1001 /
b1001 '
b1001 (
1"
#260
0"
#265
b1011 !
b1011 1
b1010 /
b1010 '
b1010 (
1"
#270
0"
#275
b1100 !
b1100 1
b1011 /
b1011 '
b1011 (
1"
#280
0"
#285
b1101 !
b1101 1
b1100 /
b1100 '
b1100 (
1"
#290
0"
#295
b1110 !
b1110 1
b1101 /
b1101 '
b1101 (
1"
#300
0"
#305
b1111 !
b1111 1
b1110 /
b1110 '
b1110 (
1"
#310
0"
#315
b10000 !
b10000 1
b1111 /
b1111 '
b1111 (
1"
#320
0"
#325
b10001 !
b10001 1
b10000 /
b10000 '
b10000 (
1"
#330
0"
#335
b10 !
b10 1
b10 +
b10 #
b0 /
b0 '
b10 )
b0 (
1"
#340
0"
#345
b11 !
b11 1
b1 /
b1 '
b1 (
1"
#350
0"
#355
b100 !
b100 1
b10 /
b10 '
b10 (
1"
#360
0"
#365
b101 !
b101 1
b11 /
b11 '
b11 (
1"
#370
0"
#375
b110 !
b110 1
b100 /
b100 '
b100 (
1"
#380
0"
#385
b111 !
b111 1
b101 /
b101 '
b101 (
1"
#390
0"
#395
b1000 !
b1000 1
b110 /
b110 '
b110 (
1"
#400
0"
#405
b1001 !
b1001 1
b111 /
b111 '
b111 (
1"
#410
0"
#415
b1010 !
b1010 1
b1000 /
b1000 '
b1000 (
1"
#420
0"
#425
b1011 !
b1011 1
b1001 /
b1001 '
b1001 (
1"
#430
0"
#435
b1100 !
b1100 1
b1010 /
b1010 '
b1010 (
1"
#440
0"
#445
b1101 !
b1101 1
b1011 /
b1011 '
b1011 (
1"
#450
0"
#455
b1110 !
b1110 1
b1100 /
b1100 '
b1100 (
1"
#460
0"
#465
b1111 !
b1111 1
b1101 /
b1101 '
b1101 (
1"
#470
0"
#475
b10000 !
b10000 1
b1110 /
b1110 '
b1110 (
1"
#480
0"
#485
b10001 !
b10001 1
b1111 /
b1111 '
b1111 (
1"
#490
0"
#495
b10010 !
b10010 1
b10000 /
b10000 '
b10000 (
1"
#500
0"
#505
b11 !
b11 1
b11 +
b11 #
b0 /
b0 '
b11 )
b0 (
1"
#510
0"
#515
b100 !
b100 1
b1 /
b1 '
b1 (
1"
#520
0"
#525
b101 !
b101 1
b10 /
b10 '
b10 (
1"
#530
0"
#535
b110 !
b110 1
b11 /
b11 '
b11 (
1"
#540
0"
#545
b111 !
b111 1
b100 /
b100 '
b100 (
1"
#550
0"
#555
b1000 !
b1000 1
b101 /
b101 '
b101 (
1"
#560
0"
#565
b1001 !
b1001 1
b110 /
b110 '
b110 (
1"
#570
0"
#575
b1010 !
b1010 1
b111 /
b111 '
b111 (
1"
#580
0"
#585
b1011 !
b1011 1
b1000 /
b1000 '
b1000 (
1"
#590
0"
#595
b1100 !
b1100 1
b1001 /
b1001 '
b1001 (
1"
#600
0"
#605
b1101 !
b1101 1
b1010 /
b1010 '
b1010 (
1"
#610
0"
#615
b1110 !
b1110 1
b1011 /
b1011 '
b1011 (
1"
#620
0"
#625
b1111 !
b1111 1
b1100 /
b1100 '
b1100 (
1"
#630
0"
#635
b10000 !
b10000 1
b1101 /
b1101 '
b1101 (
1"
#640
0"
#645
b10001 !
b10001 1
b1110 /
b1110 '
b1110 (
1"
#650
0"
#655
b10010 !
b10010 1
b1111 /
b1111 '
b1111 (
1"
#660
0"
#665
b10011 !
b10011 1
b10000 /
b10000 '
b10000 (
1"
#670
0"
#675
b100 !
b100 1
b100 +
b100 #
b0 /
b0 '
b100 )
b0 (
1"
#680
0"
#685
b101 !
b101 1
b1 /
b1 '
b1 (
1"
#690
0"
#695
b110 !
b110 1
b10 /
b10 '
b10 (
1"
#700
0"
#705
b111 !
b111 1
b11 /
b11 '
b11 (
1"
#710
0"
#715
b1000 !
b1000 1
b100 /
b100 '
b100 (
1"
#720
0"
#725
b1001 !
b1001 1
b101 /
b101 '
b101 (
1"
#730
0"
#735
b1010 !
b1010 1
b110 /
b110 '
b110 (
1"
#740
0"
#745
b1011 !
b1011 1
b111 /
b111 '
b111 (
1"
#750
0"
#755
b1100 !
b1100 1
b1000 /
b1000 '
b1000 (
1"
#760
0"
#765
b1101 !
b1101 1
b1001 /
b1001 '
b1001 (
1"
#770
0"
#775
b1110 !
b1110 1
b1010 /
b1010 '
b1010 (
1"
#780
0"
#785
b1111 !
b1111 1
b1011 /
b1011 '
b1011 (
1"
#790
0"
#795
b10000 !
b10000 1
b1100 /
b1100 '
b1100 (
1"
#800
0"
#805
b10001 !
b10001 1
b1101 /
b1101 '
b1101 (
1"
#810
0"
#815
b10010 !
b10010 1
b1110 /
b1110 '
b1110 (
1"
#820
0"
#825
b10011 !
b10011 1
b1111 /
b1111 '
b1111 (
1"
#830
0"
#835
b10100 !
b10100 1
b10000 /
b10000 '
b10000 (
1"
#840
0"
#845
b101 !
b101 1
b101 +
b101 #
b0 /
b0 '
b101 )
b0 (
1"
#850
0"
#855
b110 !
b110 1
b1 /
b1 '
b1 (
1"
#860
0"
#865
b111 !
b111 1
b10 /
b10 '
b10 (
1"
#870
0"
#875
b1000 !
b1000 1
b11 /
b11 '
b11 (
1"
#880
0"
#885
b1001 !
b1001 1
b100 /
b100 '
b100 (
1"
#890
0"
#895
b1010 !
b1010 1
b101 /
b101 '
b101 (
1"
#900
0"
#905
b1011 !
b1011 1
b110 /
b110 '
b110 (
1"
#910
0"
#915
b1100 !
b1100 1
b111 /
b111 '
b111 (
1"
#920
0"
#925
b1101 !
b1101 1
b1000 /
b1000 '
b1000 (
1"
#930
0"
#935
b1110 !
b1110 1
b1001 /
b1001 '
b1001 (
1"
#940
0"
#945
b1111 !
b1111 1
b1010 /
b1010 '
b1010 (
1"
#950
0"
#955
b10000 !
b10000 1
b1011 /
b1011 '
b1011 (
1"
#960
0"
#965
b10001 !
b10001 1
b1100 /
b1100 '
b1100 (
1"
#970
0"
#975
b10010 !
b10010 1
b1101 /
b1101 '
b1101 (
1"
#980
0"
#985
b10011 !
b10011 1
b1110 /
b1110 '
b1110 (
1"
#990
0"
#995
b10100 !
b10100 1
b1111 /
b1111 '
b1111 (
1"
#1000
0"
#1005
b10101 !
b10101 1
b10000 /
b10000 '
b10000 (
1"
#1010
0"
#1015
b110 !
b110 1
b110 +
b110 #
b0 /
b0 '
b110 )
b0 (
1"
#1020
0"
#1025
b111 !
b111 1
b1 /
b1 '
b1 (
1"
#1030
0"
#1035
b1000 !
b1000 1
b10 /
b10 '
b10 (
1"
#1040
0"
#1045
b1001 !
b1001 1
b11 /
b11 '
b11 (
1"
#1050
0"
#1055
b1010 !
b1010 1
b100 /
b100 '
b100 (
1"
#1060
0"
#1065
b1011 !
b1011 1
b101 /
b101 '
b101 (
1"
#1070
0"
#1075
b1100 !
b1100 1
b110 /
b110 '
b110 (
1"
#1080
0"
#1085
b1101 !
b1101 1
b111 /
b111 '
b111 (
1"
#1090
0"
#1095
b1110 !
b1110 1
b1000 /
b1000 '
b1000 (
1"
#1100
0"
#1105
b1111 !
b1111 1
b1001 /
b1001 '
b1001 (
1"
#1110
0"
#1115
b10000 !
b10000 1
b1010 /
b1010 '
b1010 (
1"
#1120
0"
#1125
b10001 !
b10001 1
b1011 /
b1011 '
b1011 (
1"
#1130
0"
#1135
b10010 !
b10010 1
b1100 /
b1100 '
b1100 (
1"
#1140
0"
#1145
b10011 !
b10011 1
b1101 /
b1101 '
b1101 (
1"
#1150
0"
#1155
b10100 !
b10100 1
b1110 /
b1110 '
b1110 (
1"
#1160
0"
#1165
b10101 !
b10101 1
b1111 /
b1111 '
b1111 (
1"
#1170
0"
#1175
b10110 !
b10110 1
b10000 /
b10000 '
b10000 (
1"
#1180
0"
#1185
b111 !
b111 1
b111 +
b111 #
b0 /
b0 '
b111 )
b0 (
1"
#1190
0"
#1195
b1000 !
b1000 1
b1 /
b1 '
b1 (
1"
#1200
0"
#1205
b1001 !
b1001 1
b10 /
b10 '
b10 (
1"
#1210
0"
#1215
b1010 !
b1010 1
b11 /
b11 '
b11 (
1"
#1220
0"
#1225
b1011 !
b1011 1
b100 /
b100 '
b100 (
1"
#1230
0"
#1235
b1100 !
b1100 1
b101 /
b101 '
b101 (
1"
#1240
0"
#1245
b1101 !
b1101 1
b110 /
b110 '
b110 (
1"
#1250
0"
#1255
b1110 !
b1110 1
b111 /
b111 '
b111 (
1"
#1260
0"
#1265
b1111 !
b1111 1
b1000 /
b1000 '
b1000 (
1"
#1270
0"
#1275
b10000 !
b10000 1
b1001 /
b1001 '
b1001 (
1"
#1280
0"
#1285
b10001 !
b10001 1
b1010 /
b1010 '
b1010 (
1"
#1290
0"
#1295
b10010 !
b10010 1
b1011 /
b1011 '
b1011 (
1"
#1300
0"
#1305
b10011 !
b10011 1
b1100 /
b1100 '
b1100 (
1"
#1310
0"
#1315
b10100 !
b10100 1
b1101 /
b1101 '
b1101 (
1"
#1320
0"
#1325
b10101 !
b10101 1
b1110 /
b1110 '
b1110 (
1"
#1330
0"
#1335
b10110 !
b10110 1
b1111 /
b1111 '
b1111 (
1"
#1340
0"
#1345
b10111 !
b10111 1
b10000 /
b10000 '
b10000 (
1"
#1350
0"
#1355
b1000 !
b1000 1
b1000 +
b1000 #
b0 /
b0 '
b1000 )
b0 (
1"
#1360
0"
#1365
b1001 !
b1001 1
b1 /
b1 '
b1 (
1"
#1370
0"
#1375
b1010 !
b1010 1
b10 /
b10 '
b10 (
1"
#1380
0"
#1385
b1011 !
b1011 1
b11 /
b11 '
b11 (
1"
#1390
0"
#1395
b1100 !
b1100 1
b100 /
b100 '
b100 (
1"
#1400
0"
#1405
b1101 !
b1101 1
b101 /
b101 '
b101 (
1"
#1410
0"
#1415
b1110 !
b1110 1
b110 /
b110 '
b110 (
1"
#1420
0"
#1425
b1111 !
b1111 1
b111 /
b111 '
b111 (
1"
#1430
0"
#1435
b10000 !
b10000 1
b1000 /
b1000 '
b1000 (
1"
#1440
0"
#1445
b10001 !
b10001 1
b1001 /
b1001 '
b1001 (
1"
#1450
0"
#1455
b10010 !
b10010 1
b1010 /
b1010 '
b1010 (
1"
#1460
0"
#1465
b10011 !
b10011 1
b1011 /
b1011 '
b1011 (
1"
#1470
0"
#1475
b10100 !
b10100 1
b1100 /
b1100 '
b1100 (
1"
#1480
0"
#1485
b10101 !
b10101 1
b1101 /
b1101 '
b1101 (
1"
#1490
0"
#1495
b10110 !
b10110 1
b1110 /
b1110 '
b1110 (
1"
#1500
0"
#1505
b10111 !
b10111 1
b1111 /
b1111 '
b1111 (
1"
#1510
0"
#1515
b11000 !
b11000 1
b10000 /
b10000 '
b10000 (
1"
#1520
0"
#1525
b1001 !
b1001 1
b1001 +
b1001 #
b0 /
b0 '
b1001 )
b0 (
1"
#1530
0"
#1535
b1010 !
b1010 1
b1 /
b1 '
b1 (
1"
#1540
0"
#1545
b1011 !
b1011 1
b10 /
b10 '
b10 (
1"
#1550
0"
#1555
b1100 !
b1100 1
b11 /
b11 '
b11 (
1"
#1560
0"
#1565
b1101 !
b1101 1
b100 /
b100 '
b100 (
1"
#1570
0"
#1575
b1110 !
b1110 1
b101 /
b101 '
b101 (
1"
#1580
0"
#1585
b1111 !
b1111 1
b110 /
b110 '
b110 (
1"
#1590
0"
#1595
b10000 !
b10000 1
b111 /
b111 '
b111 (
1"
#1600
0"
#1605
b10001 !
b10001 1
b1000 /
b1000 '
b1000 (
1"
#1610
0"
#1615
b10010 !
b10010 1
b1001 /
b1001 '
b1001 (
1"
#1620
0"
#1625
b10011 !
b10011 1
b1010 /
b1010 '
b1010 (
1"
#1630
0"
#1635
b10100 !
b10100 1
b1011 /
b1011 '
b1011 (
1"
#1640
0"
#1645
b10101 !
b10101 1
b1100 /
b1100 '
b1100 (
1"
#1650
0"
#1655
b10110 !
b10110 1
b1101 /
b1101 '
b1101 (
1"
#1660
0"
#1665
b10111 !
b10111 1
b1110 /
b1110 '
b1110 (
1"
#1670
0"
#1675
b11000 !
b11000 1
b1111 /
b1111 '
b1111 (
1"
#1680
0"
#1685
b11001 !
b11001 1
b10000 /
b10000 '
b10000 (
1"
#1690
0"
#1695
b1010 !
b1010 1
b1010 +
b1010 #
b0 /
b0 '
b1010 )
b0 (
1"
#1700
0"
#1705
b1011 !
b1011 1
b1 /
b1 '
b1 (
1"
#1710
0"
#1715
b1100 !
b1100 1
b10 /
b10 '
b10 (
1"
#1720
0"
#1725
b1101 !
b1101 1
b11 /
b11 '
b11 (
1"
#1730
0"
#1735
b1110 !
b1110 1
b100 /
b100 '
b100 (
1"
#1740
0"
#1745
b1111 !
b1111 1
b101 /
b101 '
b101 (
1"
#1750
0"
#1755
b10000 !
b10000 1
b110 /
b110 '
b110 (
1"
#1760
0"
#1765
b10001 !
b10001 1
b111 /
b111 '
b111 (
1"
#1770
0"
#1775
b10010 !
b10010 1
b1000 /
b1000 '
b1000 (
1"
#1780
0"
#1785
b10011 !
b10011 1
b1001 /
b1001 '
b1001 (
1"
#1790
0"
#1795
b10100 !
b10100 1
b1010 /
b1010 '
b1010 (
1"
#1800
0"
#1805
b10101 !
b10101 1
b1011 /
b1011 '
b1011 (
1"
#1810
0"
#1815
b10110 !
b10110 1
b1100 /
b1100 '
b1100 (
1"
#1820
0"
#1825
b10111 !
b10111 1
b1101 /
b1101 '
b1101 (
1"
#1830
0"
#1835
b11000 !
b11000 1
b1110 /
b1110 '
b1110 (
1"
#1840
0"
#1845
b11001 !
b11001 1
b1111 /
b1111 '
b1111 (
1"
#1850
0"
#1855
b11010 !
b11010 1
b10000 /
b10000 '
b10000 (
1"
#1860
0"
#1865
b1011 !
b1011 1
b1011 +
b1011 #
b0 /
b0 '
b1011 )
b0 (
1"
#1870
0"
#1875
b1100 !
b1100 1
b1 /
b1 '
b1 (
1"
#1880
0"
#1885
b1101 !
b1101 1
b10 /
b10 '
b10 (
1"
#1890
0"
#1895
b1110 !
b1110 1
b11 /
b11 '
b11 (
1"
#1900
0"
#1905
b1111 !
b1111 1
b100 /
b100 '
b100 (
1"
#1910
0"
#1915
b10000 !
b10000 1
b101 /
b101 '
b101 (
1"
#1920
0"
#1925
b10001 !
b10001 1
b110 /
b110 '
b110 (
1"
#1930
0"
#1935
b10010 !
b10010 1
b111 /
b111 '
b111 (
1"
#1940
0"
#1945
b10011 !
b10011 1
b1000 /
b1000 '
b1000 (
1"
#1950
0"
#1955
b10100 !
b10100 1
b1001 /
b1001 '
b1001 (
1"
#1960
0"
#1965
b10101 !
b10101 1
b1010 /
b1010 '
b1010 (
1"
#1970
0"
#1975
b10110 !
b10110 1
b1011 /
b1011 '
b1011 (
1"
#1980
0"
#1985
b10111 !
b10111 1
b1100 /
b1100 '
b1100 (
1"
#1990
0"
#1995
b11000 !
b11000 1
b1101 /
b1101 '
b1101 (
1"
#2000
0"
#2005
b11001 !
b11001 1
b1110 /
b1110 '
b1110 (
1"
#2010
0"
#2015
b11010 !
b11010 1
b1111 /
b1111 '
b1111 (
1"
#2020
0"
#2025
b11011 !
b11011 1
b10000 /
b10000 '
b10000 (
1"
#2030
0"
#2035
b1100 !
b1100 1
b1100 +
b1100 #
b0 /
b0 '
b1100 )
b0 (
1"
#2040
0"
#2045
b1101 !
b1101 1
b1 /
b1 '
b1 (
1"
#2050
0"
#2055
b1110 !
b1110 1
b10 /
b10 '
b10 (
1"
#2060
0"
#2065
b1111 !
b1111 1
b11 /
b11 '
b11 (
1"
#2070
0"
#2075
b10000 !
b10000 1
b100 /
b100 '
b100 (
1"
#2080
0"
#2085
b10001 !
b10001 1
b101 /
b101 '
b101 (
1"
#2090
0"
#2095
b10010 !
b10010 1
b110 /
b110 '
b110 (
1"
#2100
0"
#2105
b10011 !
b10011 1
b111 /
b111 '
b111 (
1"
#2110
0"
#2115
b10100 !
b10100 1
b1000 /
b1000 '
b1000 (
1"
#2120
0"
#2125
b10101 !
b10101 1
b1001 /
b1001 '
b1001 (
1"
#2130
0"
#2135
b10110 !
b10110 1
b1010 /
b1010 '
b1010 (
1"
#2140
0"
#2145
b10111 !
b10111 1
b1011 /
b1011 '
b1011 (
1"
#2150
0"
#2155
b11000 !
b11000 1
b1100 /
b1100 '
b1100 (
1"
#2160
0"
#2165
b11001 !
b11001 1
b1101 /
b1101 '
b1101 (
1"
#2170
0"
#2175
b11010 !
b11010 1
b1110 /
b1110 '
b1110 (
1"
#2180
0"
#2185
b11011 !
b11011 1
b1111 /
b1111 '
b1111 (
1"
#2190
0"
#2195
b11100 !
b11100 1
b10000 /
b10000 '
b10000 (
1"
#2200
0"
#2205
b1101 !
b1101 1
b1101 +
b1101 #
b0 /
b0 '
b1101 )
b0 (
1"
#2210
0"
#2215
b1110 !
b1110 1
b1 /
b1 '
b1 (
1"
#2220
0"
#2225
b1111 !
b1111 1
b10 /
b10 '
b10 (
1"
#2230
0"
#2235
b10000 !
b10000 1
b11 /
b11 '
b11 (
1"
#2240
0"
#2245
b10001 !
b10001 1
b100 /
b100 '
b100 (
1"
#2250
0"
#2255
b10010 !
b10010 1
b101 /
b101 '
b101 (
1"
#2260
0"
#2265
b10011 !
b10011 1
b110 /
b110 '
b110 (
1"
#2270
0"
#2275
b10100 !
b10100 1
b111 /
b111 '
b111 (
1"
#2280
0"
#2285
b10101 !
b10101 1
b1000 /
b1000 '
b1000 (
1"
#2290
0"
#2295
b10110 !
b10110 1
b1001 /
b1001 '
b1001 (
1"
#2300
0"
#2305
b10111 !
b10111 1
b1010 /
b1010 '
b1010 (
1"
#2310
0"
#2315
b11000 !
b11000 1
b1011 /
b1011 '
b1011 (
1"
#2320
0"
#2325
b11001 !
b11001 1
b1100 /
b1100 '
b1100 (
1"
#2330
0"
#2335
b11010 !
b11010 1
b1101 /
b1101 '
b1101 (
1"
#2340
0"
#2345
b11011 !
b11011 1
b1110 /
b1110 '
b1110 (
1"
#2350
0"
#2355
b11100 !
b11100 1
b1111 /
b1111 '
b1111 (
1"
#2360
0"
#2365
b11101 !
b11101 1
b10000 /
b10000 '
b10000 (
1"
#2370
0"
#2375
b1110 !
b1110 1
b1110 +
b1110 #
b0 /
b0 '
b1110 )
b0 (
1"
#2380
0"
#2385
b1111 !
b1111 1
b1 /
b1 '
b1 (
1"
#2390
0"
#2395
b10000 !
b10000 1
b10 /
b10 '
b10 (
1"
#2400
0"
#2405
b10001 !
b10001 1
b11 /
b11 '
b11 (
1"
#2410
0"
#2415
b10010 !
b10010 1
b100 /
b100 '
b100 (
1"
#2420
0"
#2425
b10011 !
b10011 1
b101 /
b101 '
b101 (
1"
#2430
0"
#2435
b10100 !
b10100 1
b110 /
b110 '
b110 (
1"
#2440
0"
#2445
b10101 !
b10101 1
b111 /
b111 '
b111 (
1"
#2450
0"
#2455
b10110 !
b10110 1
b1000 /
b1000 '
b1000 (
1"
#2460
0"
#2465
b10111 !
b10111 1
b1001 /
b1001 '
b1001 (
1"
#2470
0"
#2475
b11000 !
b11000 1
b1010 /
b1010 '
b1010 (
1"
#2480
0"
#2485
b11001 !
b11001 1
b1011 /
b1011 '
b1011 (
1"
#2490
0"
#2495
b11010 !
b11010 1
b1100 /
b1100 '
b1100 (
1"
#2500
0"
#2505
b11011 !
b11011 1
b1101 /
b1101 '
b1101 (
1"
#2510
0"
#2515
b11100 !
b11100 1
b1110 /
b1110 '
b1110 (
1"
#2520
0"
#2525
b11101 !
b11101 1
b1111 /
b1111 '
b1111 (
1"
#2530
0"
#2535
b11110 !
b11110 1
b10000 /
b10000 '
b10000 (
1"
#2540
0"
#2545
b1111 !
b1111 1
b1111 +
b1111 #
b0 /
b0 '
b1111 )
b0 (
1"
#2550
0"
#2555
b10000 !
b10000 1
b1 /
b1 '
b1 (
1"
#2560
0"
#2565
b10001 !
b10001 1
b10 /
b10 '
b10 (
1"
#2570
0"
#2575
b10010 !
b10010 1
b11 /
b11 '
b11 (
1"
#2580
0"
#2585
b10011 !
b10011 1
b100 /
b100 '
b100 (
1"
#2590
0"
#2595
b10100 !
b10100 1
b101 /
b101 '
b101 (
1"
#2600
0"
#2605
b10101 !
b10101 1
b110 /
b110 '
b110 (
1"
#2610
0"
#2615
b10110 !
b10110 1
b111 /
b111 '
b111 (
1"
#2620
0"
#2625
b10111 !
b10111 1
b1000 /
b1000 '
b1000 (
1"
#2630
0"
#2635
b11000 !
b11000 1
b1001 /
b1001 '
b1001 (
1"
#2640
0"
#2645
b11001 !
b11001 1
b1010 /
b1010 '
b1010 (
1"
#2650
0"
#2655
b11010 !
b11010 1
b1011 /
b1011 '
b1011 (
1"
#2660
0"
#2665
b11011 !
b11011 1
b1100 /
b1100 '
b1100 (
1"
#2670
0"
#2675
b11100 !
b11100 1
b1101 /
b1101 '
b1101 (
1"
#2680
0"
#2685
b11101 !
b11101 1
b1110 /
b1110 '
b1110 (
1"
#2690
0"
#2695
b11110 !
b11110 1
b1111 /
b1111 '
b1111 (
1"
#2700
0"
#2705
b11111 !
b11111 1
b10000 /
b10000 '
b10000 (
1"
#2710
0"
#2715
b0 +
b0 #
b1 &
b1 ,
b0 /
b0 '
b0 )
b0 (
1"
#2720
0"
#2725
b1 /
b1 '
b1 (
1"
#2730
0"
#2735
b10 /
b10 '
b10 (
1"
#2740
0"
#2745
b11 /
b11 '
b11 (
1"
#2750
0"
#2755
b100 /
b100 '
b100 (
1"
#2760
0"
#2765
b101 /
b101 '
b101 (
1"
#2770
0"
#2775
b110 /
b110 '
b110 (
1"
#2780
0"
#2785
b111 /
b111 '
b111 (
1"
#2790
0"
#2795
b1000 /
b1000 '
b1000 (
1"
#2800
0"
#2805
b1001 /
b1001 '
b1001 (
1"
#2810
0"
#2815
b1010 /
b1010 '
b1010 (
1"
#2820
0"
#2825
b1011 /
b1011 '
b1011 (
1"
#2830
0"
#2835
b1100 /
b1100 '
b1100 (
1"
#2840
0"
#2845
b1101 /
b1101 '
b1101 (
1"
#2850
0"
#2855
b1110 /
b1110 '
b1110 (
1"
#2860
0"
#2865
b1111 /
b1111 '
b1111 (
1"
#2870
0"
#2875
b10000 /
b10000 '
b10000 (
1"
#2880
0"
#2885
b1 +
b1 #
b0 /
b0 '
b1 )
b0 (
1"
#2890
0"
#2895
b1 /
b1 '
b1 (
1"
#2900
0"
#2905
b10 /
b10 '
b10 (
1"
#2910
0"
#2915
b11 /
b11 '
b11 (
1"
#2920
0"
#2925
b100 /
b100 '
b100 (
1"
#2930
0"
#2935
b101 /
b101 '
b101 (
1"
#2940
0"
#2945
b110 /
b110 '
b110 (
1"
#2950
0"
#2955
b111 /
b111 '
b111 (
1"
#2960
0"
#2965
b1000 /
b1000 '
b1000 (
1"
#2970
0"
#2975
b1001 /
b1001 '
b1001 (
1"
#2980
0"
#2985
b1010 /
b1010 '
b1010 (
1"
#2990
0"
#2995
b1011 /
b1011 '
b1011 (
1"
#3000
0"
#3005
b1100 /
b1100 '
b1100 (
1"
#3010
0"
#3015
b1101 /
b1101 '
b1101 (
1"
#3020
0"
#3025
b1110 /
b1110 '
b1110 (
1"
#3030
0"
#3035
b1111 /
b1111 '
b1111 (
1"
#3040
0"
